pytun.cpython-314-x86_64-linux-gnu.so
python_pytun-2.4.1.dist-info/METADATA
python_pytun-2.4.1.dist-info/WHEEL
python_pytun-2.4.1.dist-info/top_level.txt
python_pytun-2.4.1.dist-info/RECORD
python_pytun-2.4.1.dist-info/licenses/LICENSE
