Metadata-Version: 2.4
Name: python-pytun
Version: 2.4.1
Summary: Linux TUN/TAP wrapper for Python
Home-page: https://github.com/montag451/pytun
Author: montag451
Author-email: montag451@laposte.net
Maintainer: montag451
Maintainer-email: montag451@laposte.net
Classifier: Development Status :: 5 - Production/Stable
Classifier: Intended Audience :: Developers
Classifier: License :: OSI Approved :: MIT License
Classifier: Operating System :: POSIX :: Linux
Classifier: Programming Language :: C
Classifier: Programming Language :: Python :: 2
Classifier: Programming Language :: Python :: 3
Classifier: Topic :: Software Development :: Libraries :: Python Modules
Classifier: Topic :: System :: Networking
License-File: LICENSE
Dynamic: author
Dynamic: author-email
Dynamic: classifier
Dynamic: description
Dynamic: home-page
Dynamic: license-file
Dynamic: maintainer
Dynamic: maintainer-email
Dynamic: summary
